tank_utility/VERSION
tank_utility/__init__.py
tank_utility/__main__.py
tank_utility/auth.py
tank_utility/common.py
tank_utility/device.py
tank_utility-1.4.1.dist-info/LICENSE.txt
tank_utility-1.4.1.dist-info/METADATA
tank_utility-1.4.1.dist-info/WHEEL
tank_utility-1.4.1.dist-info/entry_points.txt
tank_utility-1.4.1.dist-info/top_level.txt
tank_utility-1.4.1.dist-info/RECORD
