Metadata-Version: 2.1
Name: tank-utility
Version: 1.4.1
Summary: A smart propane tank monitor.
Home-page: https://git.io/k20e
Author: Kris Molendyke
Author-email: kris@k20e.com
License: MIT
Keywords: propane monitor
Classifier: Programming Language :: Python :: 2.7
Classifier: Programming Language :: Python :: 3.6
License-File: LICENSE.txt
Requires-Dist: requests (>=2.0)
Requires-Dist: urllib3[secure]
Provides-Extra: dev
Requires-Dist: bumpversion ; extra == 'dev'
Requires-Dist: pylint ; extra == 'dev'
Requires-Dist: pre-commit ; extra == 'dev'
Requires-Dist: yapf ; extra == 'dev'
Provides-Extra: test
Requires-Dist: coverage ; extra == 'test'
Requires-Dist: mock ; extra == 'test'
Requires-Dist: responses ; extra == 'test'
Requires-Dist: tox ; extra == 'test'
